pocketpylife/LICENSE
pocketpylife/README.md
pocketpylife/__init__.py
pocketpylife/gridops.py
pocketpylife/hensel.py
pocketpylife/lifetree.py
pocketpylife/doc/lifetree_documentation
pocketpylife/doc/pattern_documentation
pocketpylife-0.0.1.dist-info/METADATA
pocketpylife-0.0.1.dist-info/WHEEL
pocketpylife-0.0.1.dist-info/licenses/LICENSE
pocketpylife-0.0.1.dist-info/RECORD
