Metadata-Version: 2.4
Name: pocketpylife
Version: 0.0.1
Summary: A Python package for manipulation of patterns in cellular automata.
Project-URL: Homepage, https://github.com/PKTwentyTwo/pocketpylife
Project-URL: Issues, https://github.com/PKTwentyTwo/pocketpylife/issues
Author-email: PK22 <pktwentytwo22@gmail.com>
License-Expression: MIT
License-File: LICENSE
Classifier: Operating System :: OS Independent
Classifier: Programming Language :: Python :: 3
Requires-Python: >=3.10
